exbw/__init__.py
exbw/__main__.py
exbw/bwdata.py
exbw-0.1.1.dist-info/METADATA
exbw-0.1.1.dist-info/WHEEL
exbw-0.1.1.dist-info/entry_points.txt
exbw-0.1.1.dist-info/licenses/LICENSE
exbw-0.1.1.dist-info/RECORD
